demos/__init__.py
demos-0.0.1.dist-info/LICENSE
demos-0.0.1.dist-info/METADATA
demos-0.0.1.dist-info/WHEEL
demos-0.0.1.dist-info/top_level.txt
demos-0.0.1.dist-info/RECORD
