Metadata-Version: 2.1
Name: demos
Version: 0.0.1
Summary: Wrangling election data
Home-page: https://github.com/danielsuo/demos
Author: Daniel Suo
Author-email: danielsuo@gmail.com
License: UNKNOWN
Platform: UNKNOWN
Classifier: Programming Language :: Python :: 3
Classifier: License :: OSI Approved :: MIT License
Classifier: Operating System :: OS Independent
Requires-Python: >3.6
Requires-Dist: numpy
Requires-Dist: scikit-learn
Requires-Dist: ipython
Requires-Dist: jupyter
Requires-Dist: click
Requires-Dist: tqdm
Requires-Dist: requests
Requires-Dist: matplotlib
